Metadata-Version: 2.1
Name: py-service-registry
Version: 0.1.0
Summary: Python service registry used as a service container as well as defines and boots services
Home-page: UNKNOWN
Maintainer: Omar Shaban
Maintainer-email: omars@php.net
License: MIT License
Platform: UNKNOWN
Classifier: License :: OSI Approved :: MIT License
Classifier: Programming Language :: Python :: 3.6
Classifier: Programming Language :: Python :: 3.7
Classifier: Programming Language :: Python :: 3.8
Classifier: Intended Audience :: Developers
Requires-Python: >=3.6
Provides-Extra: test
